tkapi/__init__.py
tkapi/activiteit.py
tkapi/agendapunt.py
tkapi/besluit.py
tkapi/commissie.py
tkapi/core.py
tkapi/document.py
tkapi/dossier.py
tkapi/filter.py
tkapi/fractie.py
tkapi/info.py
tkapi/kamervraag.py
tkapi/order.py
tkapi/persoon.py
tkapi/stemming.py
tkapi/tkapi.py
tkapi/vergadering.py
tkapi/verslag.py
tkapi/zaak.py
tkapi/util/__init__.py
tkapi/util/document.py
tkapi/util/queries.py
tkapi/util/util.py
tkapi-0.9.10.dist-info/licenses/LICENSE.md
tkapi-0.9.10.dist-info/METADATA
tkapi-0.9.10.dist-info/WHEEL
tkapi-0.9.10.dist-info/top_level.txt
tkapi-0.9.10.dist-info/RECORD
