Metadata-Version: 2.4
Name: tkapi
Version: 0.9.10
Summary: Python bindings and ORM for the Tweede Kamer OData API
Author-email: Open Kamer <info@openkamer.org>
License: MIT
Project-URL: Homepage, https://github.com/openkamer/tkapi
Classifier: Development Status :: 4 - Beta
Classifier: Intended Audience :: Developers
Classifier: Programming Language :: Python :: 3
Classifier: License :: OSI Approved :: MIT License
Requires-Python: >=3.8
License-File: LICENSE.md
Requires-Dist: requests>=2.13.0
Requires-Dist: python-dateutil>=2.0
Dynamic: license-file
